investimentos/__init__.py
investimentos/investimentos.py
ncc_meu_investimento-0.1.dist-info/licenses/LICENSE
ncc_meu_investimento-0.1.dist-info/METADATA
ncc_meu_investimento-0.1.dist-info/WHEEL
ncc_meu_investimento-0.1.dist-info/top_level.txt
ncc_meu_investimento-0.1.dist-info/RECORD
