Metadata-Version: 2.4
Name: ncc_meu_investimento
Version: 0.1
Summary: Uma biblioteca para cálculos de investimentos.
Home-page: https://github.com/tadrianonet/meu_investimento
Author: Robson Nicácio
Author-email: robson.nicacio@gmail.com
Classifier: Programming Language :: Python :: 3
Classifier: License :: OSI Approved :: MIT License
Classifier: Operating System :: OS Independent
Requires-Python: >=3.6
License-File: LICENSE
Dynamic: author
Dynamic: author-email
Dynamic: classifier
Dynamic: home-page
Dynamic: license-file
Dynamic: requires-python
Dynamic: summary
